[
    {
        "head":"Vivek Rajput's Portfolio",
        "projectss":"/assets/PortfolioSS.png",
        "content":"A personal portfolio showcasing my journey as a designer and developer blending creativity and technology to craft intuitive interfaces, bold visuals, and meaningful digital experiences.",
        "url":"https://thevivekrajput-techportfolio.vercel.app"
    },
    {
        "head":"JEC Linux Users Group Summer School Website",
        "projectss":"/assets/JlugSummerSS2.png",
        "content":"A personal portfolio showcasing my journey as a designer and developer blending creativity and technology to craft intuitive interfaces, bold visuals, and meaningful digital experiences.",
        "url":"https://thevivekrajput-techportfolio.vercel.app"
    }
]